{
  "usingComponents": {
    "v-header": "/components/header",
    "v-info": "/components/user/info",
    "v-order": "/components/user/order",
    "v-company": "/components/user/company",
    "v-knowledge": "/components/user/knowledge",
    "v-group": "/components/user/group",
    "v-advert": "/components/user/advert",
    "v-skip": "/components/public/skip-image",
    "v-company-select": "/components/public/company-select",
    "v-tabbar": "/components/tabbar"
  },
  "navigationStyle": "custom",
  "navigationBarTitleText": "个人中心"
}